pyftp.py
pyftp-0.1.1.dist-info/DESCRIPTION.rst
pyftp-0.1.1.dist-info/METADATA
pyftp-0.1.1.dist-info/RECORD
pyftp-0.1.1.dist-info/WHEEL
pyftp-0.1.1.dist-info/metadata.json
pyftp-0.1.1.dist-info/top_level.txt
