Metadata-Version: 2.0
Name: pyftp
Version: 0.1.1
Summary: High level ftp client wrapper based on python ftplib
Home-page: http://github.com/adyzng/pyftp/
Author: Azlan
Author-email: adyzng@gmail.com
License: BSD
Keywords: pyftp,python ftp
Platform: any
Classifier: Environment :: Console
Classifier: Environment :: Web Environment
Classifier: License :: Public Domain
Classifier: Operating System :: OS Independent
Classifier: Programming Language :: Python :: 2
Classifier: Topic :: Software Development :: Libraries :: Python Modules
Classifier: Topic :: System :: Networking
Classifier: Topic :: Utilities
